[
  {
    "op": "replace",
    "path": "/products/31/description",
    "value": "Fresh Pizza designed with Gold for turbulent performance"
  },
  {
    "op": "add",
    "path": "/products/10/categoryIds/4",
    "value": "8a58Cjtn"
  },
  {
    "op": "replace",
    "path": "/analytics/trackUserBehavior",
    "value": true
  },
  {
    "op": "replace",
    "path": "/features/reviewsEnabled",
    "value": false
  },
  {
    "op": "remove",
    "path": "/payments/supportedMethods/2"
  },
  {
    "op": "replace",
    "path": "/payments/supportedMethods/1",
    "value": "credit_card"
  },
  {
    "op": "replace",
    "path": "/payments/supportedMethods/0",
    "value": "upi"
  }
]