[
  {
    "op": "remove",
    "path": "/shipping/rates/0"
  },
  {
    "op": "replace",
    "path": "/shipping/rates/0",
    "value": {
      "country": "JN",
      "method": "express",
      "cost": 75969270.86468607,
      "estimatedDays": 13
    }
  },
  {
    "op": "replace",
    "path": "/analytics/googleAnalyticsId",
    "value": "UA-033068-7",
    "oldValue": "UA-9205616495-7"
  },
  {
    "op": "replace",
    "path": "/categories/41/name",
    "value": "Games",
    "oldValue": "do sed Excepteur proident cillum"
  },
  {
    "op": "replace",
    "path": "/categories/41/slug",
    "value": "games",
    "oldValue": "68ngnz-8"
  },
  {
    "op": "replace",
    "path": "/products/28/categoryIds/1",
    "value": "cillum et do eu"
  },
  {
    "op": "replace",
    "path": "/products/28/categoryIds/2",
    "value": "culpa occaecat id dolor"
  }
]